grocker/__init__.py
grocker/__main__.py
grocker/cleanners.py
grocker/helpers.py
grocker/loggers.py
grocker/utils.py
grocker/builders/__init__.py
grocker/builders/build.py
grocker/builders/naming.py
grocker/builders/op.py
grocker/builders/wheels.py
grocker/resources/__init__.py
grocker/resources/grocker.yaml
grocker/resources/docker/__init__.py
grocker/resources/docker/compiler-image/Dockerfile.j2
grocker/resources/docker/compiler-image/__init__.py
grocker/resources/docker/compiler-image/compile.py
grocker/resources/docker/compiler-image/provision.sh
grocker/resources/docker/root-image/Dockerfile.j2
grocker/resources/docker/root-image/__init__.py
grocker/resources/docker/root-image/provision.sh.j2
grocker/resources/docker/runner-image/Dockerfile.j2
grocker/resources/docker/runner-image/__init__.py
grocker/resources/docker/runner-image/provision.sh
grocker/resources/docker/wheel-server/Dockerfile
grocker/resources/docker/wheel-server/__init__.py
grocker/resources/docker/wheel-server/nginx.conf
grocker-8.3.dist-info/licenses/LICENSE.txt
grocker-8.3.dist-info/METADATA
grocker-8.3.dist-info/WHEEL
grocker-8.3.dist-info/entry_points.txt
grocker-8.3.dist-info/top_level.txt
grocker-8.3.dist-info/zip-safe
grocker-8.3.dist-info/RECORD
