Metadata-Version: 2.4
Name: grocker
Version: 8.3
Summary: Docker image builder
Home-page: http://github.com/polyconseil/grocker
Author: Polyconseil
Author-email: opensource+grocker@polyconseil.fr
License: BSD 3-Clause License
Keywords: docker,build,packaging
Classifier: Development Status :: 5 - Production/Stable
Classifier: Environment :: Console
Classifier: Intended Audience :: Developers
Classifier: License :: OSI Approved :: BSD License
Classifier: Natural Language :: English
Classifier: Programming Language :: Python :: 3.10
Classifier: Programming Language :: Python :: 3.11
Classifier: Programming Language :: Python :: 3.12
Classifier: Programming Language :: Python :: 3.13
Classifier: Programming Language :: Python :: 3.14
Classifier: Topic :: Software Development :: Build Tools
Classifier: Topic :: System :: Software Distribution
Requires-Python: >=3.8
License-File: LICENSE.txt
Requires-Dist: click
Requires-Dist: docker>=3.0.0
Requires-Dist: Jinja2
Requires-Dist: pip>=10
Requires-Dist: pyyaml>=3.11
Requires-Dist: packaging
Dynamic: license-file
